waifuim/__init__.py
waifuim/client.py
waifuim/exceptions.py
waifuim/models.py
waifuim/py.typed
waifuim/utils.py
waifuim-1.1.1.dist-info/LICENSE
waifuim-1.1.1.dist-info/METADATA
waifuim-1.1.1.dist-info/WHEEL
waifuim-1.1.1.dist-info/top_level.txt
waifuim-1.1.1.dist-info/RECORD
